lyricy/__init__.py
lyricy/__main__.py
lyricy/classes.py
lyricy/cli.py
lyricy/providers.py
test/__init__.py
test/test_lyricy.py
lyricy-1.4.dist-info/LICENSE
lyricy-1.4.dist-info/METADATA
lyricy-1.4.dist-info/WHEEL
lyricy-1.4.dist-info/entry_points.txt
lyricy-1.4.dist-info/top_level.txt
lyricy-1.4.dist-info/RECORD
