Metadata-Version: 2.1
Name: lyricy
Version: 1.4
Summary: A command line lyrics utility tool which     search and add lyrics to your offline songs.
Home-page: https://github.com/yogeshwaran01/lyricy
Download-URL: https://github.com/yogeshwaran01/lyricy/archive/master.zip
Author: Yogeshwaran R
Author-email: yogeshin247@gmail.com
License: MIT
Keywords: python package lyrics lrc yogeshwaran01 songs
Classifier: Programming Language :: Python :: 3
Classifier: License :: OSI Approved :: MIT License
Classifier: Operating System :: OS Independent
License-File: LICENSE
Requires-Dist: beautifulsoup4 (==4.11.1)
Requires-Dist: certifi (==2022.6.15)
Requires-Dist: charset-normalizer (==2.1.0)
Requires-Dist: click (==8.1.3)
Requires-Dist: commonmark (==0.9.1)
Requires-Dist: idna (==3.3)
Requires-Dist: music-tag (==0.4.3)
Requires-Dist: mutagen (==1.45.1)
Requires-Dist: Pygments (==2.12.0)
Requires-Dist: pylrc (==0.1.2)
Requires-Dist: requests (==2.28.1)
Requires-Dist: rich (==12.4.4)
Requires-Dist: soupsieve (==2.3.2.post1)
Requires-Dist: urllib3 (==1.26.9)
